client/__init__.py
client/add_contact.py
client/client_database.py
client/del_contact.py
client/main_window.py
client/main_window_conv.py
client/run_client.py
client/start_dialog.py
client/transport.py
client/common/__init__.py
client/common/decorators.py
client/common/descriptors.py
client/common/errors.py
client/common/metaclasses.py
client/common/utils.py
client/common/variables.py
client/logs/__init__.py
client/logs/client_log_config.py
client/logs/server_log_config.py
client/logs/logging/__init__.py
simple_socket_chat_client-0.1.2.dist-info/METADATA
simple_socket_chat_client-0.1.2.dist-info/WHEEL
simple_socket_chat_client-0.1.2.dist-info/top_level.txt
simple_socket_chat_client-0.1.2.dist-info/RECORD
